src/utils/mux.v
module mux(in1, in2, out, sel);

    parameter WIDTH = 16;

    input [WIDTH-1:0] in1, in2;
    input sel;
    output reg [WIDTH-1:0] out;

    always@(*) begin
        case(sel)
            1'b0: out <= in1; // acu
            1'b1: out <= in2; // ldi
        endcase
    end
endmodule

src/memory/registers.v
module registers(clk, rf_en, r_or_w, reg_addr, in, out);

    parameter WIDTH = 16;
    parameter REG_NUM = 16;

    input clk, rf_en, r_or_w; // r_or_w => 1 = write, 0 = read
    input [REG_NUM-1:0] reg_addr;
    input [WIDTH-1:0] in;
    output reg [WIDTH-1:0] out;

    reg [WIDTH-1:0] mem [REG_NUM-1:0];

    initial out <= 16'dz;

    always @(*) begin
        if(rf_en) begin        
            if(r_or_w) begin // write
                mem[reg_addr] <= in;
                out <= 16'dz;
            end
            else begin //read
                out <= mem[reg_addr];
            end
        end
        else out <= 16'dz;
    end

endmodule

// genvar i;
// generate
//     for (i = 0; i < REG_NUM; i = i+1) begin
//         rf register0 (
// 	        .clk(clk),
// 	        .ce(reg_sel[i]),
// 	        .in(in),
// 	        .out(out)
//         );
//     end
// endgenerate

// rf Rf_0(
// 	.clk(clk),
// 	.ce(reg_sel[0]),
// 	.in(in),
// 	.out(out)
// );

// rf Rf_1(
// 	.clk(clk),
// 	.ce(reg_sel[1]),
// 	.in(in),
// 	.out(out)
// );

// rf Rf_2(
// 	.clk(clk),
// 	.ce(reg_sel[2]),
// 	.in(in),
// 	.out(out)
// );

// rf Rf_3(
// 	.clk(clk),
// 	.ce(reg_sel[3]),
// 	.in(in),
// 	.out(out)
// );

// rf Rf_4(
// 	.clk(clk),
// 	.ce(reg_sel[4]),
// 	.in(in),
// 	.out(out)
// );

// rf Rf_5(
// 	.clk(clk),
// 	.ce(reg_sel[5]),
// 	.in(in),
// 	.out(out)
// );

// rf Rf_6(
// 	.clk(clk),
// 	.ce(reg_sel[6]),
// 	.in(in),
// 	.out(out)
// );

// rf Rf_7(
// 	.clk(clk),
// 	.ce(reg_sel[7]),
// 	.in(in),
// 	.out(out)
// );

src/basic/a.v
module a(ce, clk, in, out);

parameter WIDTH = 4;

input ce, clk;
input [WIDTH-1:0] in;
output reg [WIDTH-1:0] out;

initial out <= 16'd0;

always @(negedge clk) begin
    if(ce) out <= in;
    else out <= out; // ---
end

endmodule

src/control/instructions.v
`define NOT 8'h00
`define XOR 8'h01
`define OR  8'h02
`define AND 8'h03
`define SUB 8'h04
`define ADD 8'h05
`define RR  8'h06
`define RL  8'h07
`define DEC 8'h08
`define INC 8'h09
`define LD  8'h0A // load register -> accumulator
`define ST  8'h0B // store accumulator -> register
`define NOP 8'h0C
`define LDI 8'h0D // load rom -> accumulator
`define JMP 8'h0E
`define RST 8'h0F
`define Call // skok z adresem powrotu
`define return // adres powrotu

/*
    case(instr)
        4'd0:     {rst, decoded} <= {1'b0, `NOT}; // not
        4'd1:     {rst, decoded} <= {1'b0, `XOR}; // xor
        4'd2:     {rst, decoded} <= {1'b0, `OR};  // or
        4'd3:     {rst, decoded} <= {1'b0, `AND}; // and
        4'd4:     {rst, decoded} <= {1'b0, `SUB}; // sub
        4'd5:     {rst, decoded} <= {1'b0, `ADD}; // add
        4'd6:     {rst, decoded} <= {1'b0, `RR};  // rr
        4'd7:     {rst, decoded} <= {1'b0, `RL};  // rl
        4'd8:     {rst, decoded} <= {1'b0, `DEC}; // dec
        4'd9:     {rst, decoded} <= {1'b0, `INC}; // inc
        4'd10:    {rst, decoded} <= {1'b0, `LD};  // ld
        4'd11:    {rst, decoded} <= {1'b0, `ST};  // st
        4'd12:    {rst, decoded} <= {1'b0, `NOP}; // nop
        4'd13:    {rst, decoded} <= {1'b0, `NOP}; // nop
        4'd14:    {rst, decoded} <= {1'b1, `RST}; // rst
        4'd15:    {rst, decoded} <= {1'b1, `RST}; // rst
        default:  {rst, decoded} <= {1'b1, `RST}; // rst
    endcase
*/

src/basic/alu.v
`include "./src/control/instructions.v"

module alu(in1, in2, op, funct, zero, overflow, out);

parameter WIDTH = 16;

input [WIDTH-1:0] in1, in2;
input [7:0] op;
input funct;

output reg [WIDTH-1:0] out;

output reg zero;
output reg overflow;

always @(*) begin
    case(op)
        `NOT:   out <= !in1;
        `XOR:   out <= in1 ^ in2;
        `OR:    out <= in1 | in2;
        `AND:   out <= in1 & in2;
        `SUB:   out <= in1 - in2;
        `ADD:   out <= in1 + in2;
        `RR:    out <= {in1[0], in1[(WIDTH-1):1]};
        `RL:    out <= {in1[(WIDTH-2):0], in1[(WIDTH-1)]};
        `DEC:   out <= in1 - 1'b1;
        `INC:   out <= in1 + 1'b1;
        `LD:    out <= in2;
        `ST:    out <= 16'd0;
        `NOP:   out <= 16'd0;
        `LDI:   out <= in1;
        `JMP:   out <= 16'd0;
        `RST:   out <= 16'd0;
        default: out <= 16'd0;
    endcase
    zero <= (out==0)?1:0;

end

endmodule

src/control/id.v
`timescale 1ns/1ps
`include "./src/control/instructions.v"

module id (instr, op, ldi, rf_en, acu_en, rst, jmp_en, r_or_w);

    parameter INSTR_WIDTH = 2;
    parameter OP_WIDTH = 4;

    input [7:0] instr;
    output reg [7:0] op;
    output reg rst, ldi, rf_en, acu_en, jmp_en, r_or_w;

    initial {rst, ldi, r_or_w, rf_en, acu_en, jmp_en} = {6'b0_0_0_010};


    always @(*) begin
        case(instr)
            8'd0:     {rst, ldi, r_or_w, rf_en, acu_en, jmp_en, op} <= {6'b0_0_0_010, `NOT}; // not
            8'd1:     {rst, ldi, r_or_w, rf_en, acu_en, jmp_en, op} <= {6'b0_0_0_110, `XOR}; // xor
            8'd2:     {rst, ldi, r_or_w, rf_en, acu_en, jmp_en, op} <= {6'b0_0_0_110, `OR};  // or
            8'd3:     {rst, ldi, r_or_w, rf_en, acu_en, jmp_en, op} <= {6'b0_0_0_110, `AND}; // and
            8'd4:     {rst, ldi, r_or_w, rf_en, acu_en, jmp_en, op} <= {6'b0_0_0_110, `SUB}; // sub
            8'd5:     {rst, ldi, r_or_w, rf_en, acu_en, jmp_en, op} <= {6'b0_0_0_110, `ADD}; // add
            8'd6:     {rst, ldi, r_or_w, rf_en, acu_en, jmp_en, op} <= {6'b0_0_0_010, `RR};  // rr
            8'd7:     {rst, ldi, r_or_w, rf_en, acu_en, jmp_en, op} <= {6'b0_0_0_010, `RL};  // rl
            8'd8:     {rst, ldi, r_or_w, rf_en, acu_en, jmp_en, op} <= {6'b0_0_0_010, `DEC}; // dec
            8'd9:     {rst, ldi, r_or_w, rf_en, acu_en, jmp_en, op} <= {6'b0_0_0_010, `INC}; // inc
            8'd10:    {rst, ldi, r_or_w, rf_en, acu_en, jmp_en, op} <= {6'b0_0_0_110, `LD};  // ld
            8'd11:    {rst, ldi, r_or_w, rf_en, acu_en, jmp_en, op} <= {6'b0_0_1_100, `ST};  // st
            8'd12:    {rst, ldi, r_or_w, rf_en, acu_en, jmp_en, op} <= {6'b0_0_0_000, `NOP}; // nop
            8'd13:    {rst, ldi, r_or_w, rf_en, acu_en, jmp_en, op} <= {6'b0_1_0_010, `LDI}; // ldi
            8'd14:    {rst, ldi, r_or_w, rf_en, acu_en, jmp_en, op} <= {6'b0_0_0_001, `JMP}; // jmp
            8'd15:    {rst, ldi, r_or_w, rf_en, acu_en, jmp_en, op} <= {6'b1_0_0_000, `RST}; // rst
            8'd16:    {rst, ldi, r_or_w, rf_en, acu_en, jmp_en, op} <= {6'b1_0_0_000, `RST}; // rst
            8'd17:    {rst, ldi, r_or_w, rf_en, acu_en, jmp_en, op} <= {6'b1_0_0_000, `RST}; // rst
            8'd18:    {rst, ldi, r_or_w, rf_en, acu_en, jmp_en, op} <= {6'b1_0_0_000, `RST}; // rst
            8'd19:    {rst, ldi, r_or_w, rf_en, acu_en, jmp_en, op} <= {6'b1_0_0_000, `RST}; // rst
            8'd20:    {rst, ldi, r_or_w, rf_en, acu_en, jmp_en, op} <= {6'b1_0_0_000, `RST}; // rst
            8'd21:    {rst, ldi, r_or_w, rf_en, acu_en, jmp_en, op} <= {6'b1_0_0_000, `RST}; // rst
            8'd22:    {rst, ldi, r_or_w, rf_en, acu_en, jmp_en, op} <= {6'b1_0_0_000, `RST}; // rst
            8'd23:    {rst, ldi, r_or_w, rf_en, acu_en, jmp_en, op} <= {6'b1_0_0_000, `RST}; // rst
            8'd23:    {rst, ldi, r_or_w, rf_en, acu_en, jmp_en, op} <= {6'b1_0_0_000, `RST}; // rst
            8'd24:    {rst, ldi, r_or_w, rf_en, acu_en, jmp_en, op} <= {6'b1_0_0_000, `RST}; // rst
            8'd25:    {rst, ldi, r_or_w, rf_en, acu_en, jmp_en, op} <= {6'b1_0_0_000, `RST}; // rst
            8'd26:    {rst, ldi, r_or_w, rf_en, acu_en, jmp_en, op} <= {6'b1_0_0_000, `RST}; // rst
            8'd27:    {rst, ldi, r_or_w, rf_en, acu_en, jmp_en, op} <= {6'b1_0_0_000, `RST}; // rst
            8'd28:    {rst, ldi, r_or_w, rf_en, acu_en, jmp_en, op} <= {6'b1_0_0_000, `RST}; // rst
            8'd29:    {rst, ldi, r_or_w, rf_en, acu_en, jmp_en, op} <= {6'b1_0_0_000, `RST}; // rst
            8'd30:    {rst, ldi, r_or_w, rf_en, acu_en, jmp_en, op} <= {6'b1_0_0_000, `RST}; // rst
            8'd31:    {rst, ldi, r_or_w, rf_en, acu_en, jmp_en, op} <= {6'b1_0_0_000, `RST}; // rst
        endcase
    end
endmodule

src/memory/rom.v
`timescale 1ns/1ps
`include "./src/control/instructions.v"

module rom(addr, data);

parameter RAM_WORD_WIDTH = 24;
parameter RAM_ADDR_BITS = 4;

input [(2**RAM_ADDR_BITS)-1 : 0] addr;
output reg [RAM_WORD_WIDTH-1 : 0] data;


reg [RAM_WORD_WIDTH-1:0] mem [(2**RAM_ADDR_BITS)-1:0];

// test
initial begin
	mem [0]  = {`NOP,	16'h0};
	mem [1]  = {`LDI,	16'h5};
	mem [2]  = {`ST,	16'h1};
	mem [3]  = {`LDI,	16'h3};
	mem [4]  = {`ADD,	16'h1};
	mem [5]  = {`ST,	16'h2};
	mem [6]  = {`NOP,	16'h0};
	mem [7]  = {`NOP, 	16'h0};
	mem [8]  = {`LD, 	16'h2};
	mem [9]  = {`INC,	16'h0};
	mem [10] = {`JMP,	16'h9};
	mem [11] = {`RST,	16'h0};
	
	// mem [0]  = {`NOP,	16'h0};
	// mem [1]  = {`LDI,	16'h5};
	// mem [2]  = {`ST,	16'h1};
	// mem [3]  = {`LDI,	16'h3};
	// mem [4]  = {`ST,	16'h1};
	// mem [5]  = {`LD,	16'h0};
	// mem [6]  = {`ST,	16'h2};
	// mem [7]  = {`LD, 	16'h0};
	// mem [8]  = {`ADD, 	16'h2};
	// mem [9]  = {`RST,	16'h0};
end

always @(*) begin
    data <= mem[addr];
end

endmodule

src/control/counter.v
`timescale 1ns/1ps

module counter(clk, rst, jmp_en, jmp_addr, pc);
    input clk;
    input rst;
	input jmp_en;
	input [15:0] jmp_addr;

    output reg [15:0] pc;

    
    initial pc = 16'd0;    
    
    always @(negedge clk)
    begin
        if(rst == 1)
            pc <= 16'd0;
        else
        begin
            if(jmp_en == 1)
                pc <= jmp_addr;
            else
                pc <= pc + 1;
        end
    end
endmodule

processor.v
`timescale 1ns/1ps

module processor(clk_in, rst_in);

	input clk_in;
	input rst_in;
	reg rst = 1'b0;

	wire rst_id, ldi, acu_en, rf_en, jmp_en;
	wire[15:0] pc_bits;
	wire[23:0] rom_data; // 8op + 16data
	wire[15:0] alu_out;
	wire[15:0] acu_out;
	wire[15:0] reg_out;
	wire[15:0] mux_out;

	wire[7:0] op;

	wire r_or_w;
	wire alu_zero;
	wire alu_overflow;

	always @(*) rst <= rst_in || rst_id;


	counter ProgramCounter(
		.clk(clk_in),
		.rst(rst),
		.jmp_en(jmp_en),
		.jmp_addr(jmp_en ? rom_data[15:0] : 16'bz),
		.pc(pc_bits)
	);

	rom #(.RAM_WORD_WIDTH(24), .RAM_ADDR_BITS(4)) Rom
	(	.addr(pc_bits),
		.data(rom_data));

	id InstructionDecoder(
		.instr(rom_data[23:16]),
		.op(op),
		.rst(rst_id),
		.ldi(ldi),
		.acu_en(acu_en),
		.rf_en(rf_en),
		.jmp_en(jmp_en),
		.r_or_w(r_or_w)
	);

	alu #(.WIDTH(16)) Alu(
		.in1(mux_out),
		.in2(reg_out),
		.op(op),
	    .zero(alu_zero),
	    .overflow(alu_overflow),
		.out(alu_out)
	);

	a #(.WIDTH(16)) Accumulator(
		.clk(clk_in),
		.ce(acu_en),
		.in(alu_out),
		.out(acu_out)
	);

	registers #(.REG_NUM(16), .WIDTH(16)) Registers(
		.clk(clk_in),
		.rf_en(rf_en),
		.r_or_w(r_or_w),
		.reg_addr(rf_en ? rom_data[15:0] : 16'bz),
		.in(acu_out),
		.out(reg_out)
	);

	mux #(.WIDTH(16)) Mux(
		.in1(acu_out),
		.in2(rom_data[15:0]),
		.out(mux_out),
		.sel(ldi)
	);

endmodule

tests/processor_tb.v
`timescale 1ns/1ps

module processor_tb;
integer i;

// Clock and reset signals
reg clk = 1'b1;
reg rst = 1'b0;

// Design Inputs and outputs
// wire out [3:0];

// DUT instantiation
processor P(
    .clk_in(clk),
    .rst_in(rst)
);

// generate the clock
// initial begin
//     clk = 1'b0;
//     forever #1 clk = ~clk;
// end

// Generate the reset
// initial begin
//     reset = 1'b1;
//     #10
//     reset = 1'b0;
// end

// Test stimulus
initial begin

    // Use the monitor task to display the FPGA IO
    // $monitor("time=%3d, q=%2b \n", $time, out);

    // Generate each input with a 20 ns delay between them
    for (i = 0; i<50; i++) begin
        #1 clk = ~clk;        
    end
    #10
    $finish;
end

initial begin
    $dumpfile("tests/up_tb.vcd");
    $dumpvars(0, processor_tb);
    $dumpon;
end

endmodule

tests/up_tb.vcd
$date
	Fri Jan 19 15:48:55 2024
$end
$version
	Icarus Verilog
$end
$timescale
	1ps
$end
$scope module processor_tb $end
$var reg 1 ! clk $end
$var reg 1 " rst $end
$var integer 32 # i [31:0] $end
$scope module P $end
$var wire 1 ! clk_in $end
$var wire 1 " rst_in $end
$var wire 1 $ rst_id $end
$var wire 24 % rom_data [23:0] $end
$var wire 1 & rf_en $end
$var wire 16 ' reg_out [15:0] $end
$var wire 1 ( r_or_w $end
$var wire 16 ) pc_bits [15:0] $end
$var wire 8 * op [7:0] $end
$var wire 16 + mux_out [15:0] $end
$var wire 1 , ldi $end
$var wire 1 - jmp_en $end
$var wire 1 . alu_zero $end
$var wire 1 / alu_overflow $end
$var wire 16 0 alu_out [15:0] $end
$var wire 16 1 acu_out [15:0] $end
$var wire 1 2 acu_en $end
$var reg 1 3 rst $end
$scope module Accumulator $end
$var wire 1 ! clk $end
$var wire 16 4 in [15:0] $end
$var wire 1 2 ce $end
$var parameter 32 5 WIDTH $end
$var reg 16 6 out [15:0] $end
$upscope $end
$scope module Alu $end
$var wire 1 7 funct $end
$var wire 8 8 op [7:0] $end
$var wire 16 9 in2 [15:0] $end
$var wire 16 : in1 [15:0] $end
$var parameter 32 ; WIDTH $end
$var reg 16 < out [15:0] $end
$var reg 1 / overflow $end
$var reg 1 . zero $end
$upscope $end
$scope module InstructionDecoder $end
$var wire 8 = instr [7:0] $end
$var parameter 32 > INSTR_WIDTH $end
$var parameter 32 ? OP_WIDTH $end
$var reg 1 2 acu_en $end
$var reg 1 - jmp_en $end
$var reg 1 , ldi $end
$var reg 8 @ op [7:0] $end
$var reg 1 ( r_or_w $end
$var reg 1 & rf_en $end
$var reg 1 $ rst $end
$upscope $end
$scope module Mux $end
$var wire 16 A in1 [15:0] $end
$var wire 16 B in2 [15:0] $end
$var wire 1 , sel $end
$var parameter 32 C WIDTH $end
$var reg 16 D out [15:0] $end
$upscope $end
$scope module ProgramCounter $end
$var wire 1 ! clk $end
$var wire 16 E jmp_addr [15:0] $end
$var wire 1 - jmp_en $end
$var wire 1 3 rst $end
$var reg 16 F pc [15:0] $end
$upscope $end
$scope module Registers $end
$var wire 1 ! clk $end
$var wire 16 G in [15:0] $end
$var wire 1 ( r_or_w $end
$var wire 16 H reg_addr [15:0] $end
$var wire 1 & rf_en $end
$var parameter 32 I REG_NUM $end
$var parameter 32 J WIDTH $end
$var reg 16 K out [15:0] $end
$upscope $end
$scope module Rom $end
$var wire 16 L addr [15:0] $end
$var parameter 32 M RAM_ADDR_BITS $end
$var parameter 32 N RAM_WORD_WIDTH $end
$var reg 24 O data [23:0] $end
$upscope $end
$upscope $end
$upscope $end
$enddefinitions $end
$comment Show the parameter values. $end
$dumpall
b11000 N
b100 M
b10000 J
b10000 I
b10000 C
b100 ?
b10 >
b10000 ;
b10000 5
$end
#0
$dumpvars
b11000000000000000000 O
b0 L
bz K
bz H
b0 G
b0 F
bz E
b0 D
b0 B
b0 A
b1100 @
b1100 =
b0 <
b0 :
bz 9
b1100 8
z7
b0 6
b0 4
03
02
b0 1
b0 0
x/
1.
0-
0,
b0 +
b1100 *
b0 )
0(
bz '
0&
b11000000000000000000 %
0$
b0 #
0"
1!
$end
#1000
0.
b101 0
b101 4
b101 <
b101 +
b101 :
b101 D
1,
12
b1101 *
b1101 8
b1101 @
b101 B
b1101 =
b11010000000000000101 %
b11010000000000000101 O
b1 )
b1 F
b1 L
b1 #
0!
#2000
b10 #
1!
#3000
1.
b0 0
b0 4
b0 <
b1 H
b101 +
b101 :
b101 D
0,
1(
1&
02
b1011 *
b1011 8
b1011 @
b1 B
b1011 =
b10110000000000000001 %
b10110000000000000001 O
b101 1
b101 6
b101 A
b101 G
b10 )
b10 F
b10 L
b11 #
0!
#4000
b100 #
1!
#5000
0.
b11 +
b11 :
b11 D
b11 0
b11 4
b11 <
1,
0(
0&
12
b1101 *
b1101 8
b1101 @
bz H
b11 B
b1101 =
b11010000000000000011 %
b11010000000000000011 O
b11 )
b11 F
b11 L
b101 #
0!
#6000
b110 #
1!
#7000
0.
b101 '
b101 9
b101 K
b1000 0
b1000 4
b1000 <
b1 H
b11 +
b11 :
b11 D
0,
1&
b101 *
b101 8
b101 @
b1 B
b101 =
b1010000000000000001 %
b1010000000000000001 O
b11 1
b11 6
b11 A
b11 G
b100 )
b100 F
b100 L
b111 #
0!
#8000
b1000 #
1!
#9000
1.
bz '
bz 9
bz K
1(
02
b1011 *
b1011 8
b1011 @
b0 0
b0 4
b0 <
b10 H
b10 B
b1011 =
b10110000000000000010 %
b10110000000000000010 O
b1000 +
b1000 :
b1000 D
b101 )
b101 F
b101 L
b1000 1
b1000 6
b1000 A
b1000 G
b1001 #
0!
#10000
b1010 #
1!
#11000
0(
0&
b1100 *
b1100 8
b1100 @
bz H
b0 B
b1100 =
b11000000000000000000 %
b11000000000000000000 O
b110 )
b110 F
b110 L
b1011 #
0!
#12000
b1100 #
1!
#13000
b111 )
b111 F
b111 L
b1101 #
0!
#14000
b1110 #
1!
#15000
0.
b1000 '
b1000 9
b1000 K
b1000 0
b1000 4
b1000 <
b10 H
1&
12
b1010 *
b1010 8
b1010 @
b10 B
b1010 =
b10100000000000000010 %
b10100000000000000010 O
b1000 )
b1000 F
b1000 L
b1111 #
0!
#16000
b10000 #
1!
#17000
bz '
bz 9
bz K
b1001 0
b1001 4
b1001 <
0&
b1001 *
b1001 8
b1001 @
bz H
b0 B
b1001 =
b10010000000000000000 %
b10010000000000000000 O
b1001 )
b1001 F
b1001 L
b10001 #
0!
#18000
b10010 #
1!
#19000
1.
b1001 E
02
1-
b1110 *
b1110 8
b1110 @
b0 0
b0 4
b0 <
b1001 B
b1110 =
b1001 +
b1001 :
b1001 D
b11100000000000001001 %
b11100000000000001001 O
b1001 1
b1001 6
b1001 A
b1001 G
b1010 )
b1010 F
b1010 L
b10011 #
0!
#20000
b10100 #
1!
#21000
0.
b1010 0
b1010 4
b1010 <
12
0-
b1001 *
b1001 8
b1001 @
bz E
b0 B
b1001 =
b10010000000000000000 %
b10010000000000000000 O
b1001 )
b1001 F
b1001 L
b10101 #
0!
#22000
b10110 #
1!
#23000
1.
b1001 E
02
1-
b1110 *
b1110 8
b1110 @
b0 0
b0 4
b0 <
b1001 B
b1110 =
b1010 +
b1010 :
b1010 D
b11100000000000001001 %
b11100000000000001001 O
b1010 1
b1010 6
b1010 A
b1010 G
b1010 )
b1010 F
b1010 L
b10111 #
0!
#24000
b11000 #
1!
#25000
0.
b1011 0
b1011 4
b1011 <
12
0-
b1001 *
b1001 8
b1001 @
bz E
b0 B
b1001 =
b10010000000000000000 %
b10010000000000000000 O
b1001 )
b1001 F
b1001 L
b11001 #
0!
#26000
b11010 #
1!
#27000
1.
b1001 E
02
1-
b1110 *
b1110 8
b1110 @
b0 0
b0 4
b0 <
b1001 B
b1110 =
b1011 +
b1011 :
b1011 D
b11100000000000001001 %
b11100000000000001001 O
b1011 1
b1011 6
b1011 A
b1011 G
b1010 )
b1010 F
b1010 L
b11011 #
0!
#28000
b11100 #
1!
#29000
0.
b1100 0
b1100 4
b1100 <
12
0-
b1001 *
b1001 8
b1001 @
bz E
b0 B
b1001 =
b10010000000000000000 %
b10010000000000000000 O
b1001 )
b1001 F
b1001 L
b11101 #
0!
#30000
b11110 #
1!
#31000
1.
b1001 E
02
1-
b1110 *
b1110 8
b1110 @
b0 0
b0 4
b0 <
b1001 B
b1110 =
b1100 +
b1100 :
b1100 D
b11100000000000001001 %
b11100000000000001001 O
b1100 1
b1100 6
b1100 A
b1100 G
b1010 )
b1010 F
b1010 L
b11111 #
0!
#32000
b100000 #
1!
#33000
0.
b1101 0
b1101 4
b1101 <
12
0-
b1001 *
b1001 8
b1001 @
bz E
b0 B
b1001 =
b10010000000000000000 %
b10010000000000000000 O
b1001 )
b1001 F
b1001 L
b100001 #
0!
#34000
b100010 #
1!
#35000
1.
b1001 E
02
1-
b1110 *
b1110 8
b1110 @
b0 0
b0 4
b0 <
b1001 B
b1110 =
b1101 +
b1101 :
b1101 D
b11100000000000001001 %
b11100000000000001001 O
b1101 1
b1101 6
b1101 A
b1101 G
b1010 )
b1010 F
b1010 L
b100011 #
0!
#36000
b100100 #
1!
#37000
0.
b1110 0
b1110 4
b1110 <
12
0-
b1001 *
b1001 8
b1001 @
bz E
b0 B
b1001 =
b10010000000000000000 %
b10010000000000000000 O
b1001 )
b1001 F
b1001 L
b100101 #
0!
#38000
b100110 #
1!
#39000
1.
b1001 E
02
1-
b1110 *
b1110 8
b1110 @
b0 0
b0 4
b0 <
b1001 B
b1110 =
b1110 +
b1110 :
b1110 D
b11100000000000001001 %
b11100000000000001001 O
b1110 1
b1110 6
b1110 A
b1110 G
b1010 )
b1010 F
b1010 L
b100111 #
0!
#40000
b101000 #
1!
#41000
0.
b1111 0
b1111 4
b1111 <
12
0-
b1001 *
b1001 8
b1001 @
bz E
b0 B
b1001 =
b10010000000000000000 %
b10010000000000000000 O
b1001 )
b1001 F
b1001 L
b101001 #
0!
#42000
b101010 #
1!
#43000
1.
b1001 E
02
1-
b1110 *
b1110 8
b1110 @
b0 0
b0 4
b0 <
b1001 B
b1110 =
b1111 +
b1111 :
b1111 D
b11100000000000001001 %
b11100000000000001001 O
b1111 1
b1111 6
b1111 A
b1111 G
b1010 )
b1010 F
b1010 L
b101011 #
0!
#44000
b101100 #
1!
#45000
0.
b10000 0
b10000 4
b10000 <
12
0-
b1001 *
b1001 8
b1001 @
bz E
b0 B
b1001 =
b10010000000000000000 %
b10010000000000000000 O
b1001 )
b1001 F
b1001 L
b101101 #
0!
#46000
b101110 #
1!
#47000
1.
b1001 E
02
1-
b1110 *
b1110 8
b1110 @
b0 0
b0 4
b0 <
b1001 B
b1110 =
b10000 +
b10000 :
b10000 D
b11100000000000001001 %
b11100000000000001001 O
b10000 1
b10000 6
b10000 A
b10000 G
b1010 )
b1010 F
b1010 L
b101111 #
0!
#48000
b110000 #
1!
#49000
0.
b10001 0
b10001 4
b10001 <
12
0-
b1001 *
b1001 8
b1001 @
bz E
b0 B
b1001 =
b10010000000000000000 %
b10010000000000000000 O
b1001 )
b1001 F
b1001 L
b110001 #
0!
#50000
b110010 #
1!
