src/utils/stack.v
module stack (clk, rst, push, pop, data_in, data_out, full, empty);
    integer i;
    parameter WIDTH = 16;
    parameter DEPTH = 8;
    
    input clk;      // Zegar
    input rst;      // Sygnał resetu
    input push;     // Sygnał PUSH
    input pop;      // Sygnał POP
    input [WIDTH-1:0] data_in;  // Dane do umieszczenia na stosie
    output [WIDTH-1:0] data_out; // Dane pobrane ze stosu
    output reg full;      // Flaga pełnego stosu
    output reg empty;     // Flaga pustego stosu

    reg [WIDTH-1:0] mem [0:DEPTH-1]; // Stos o wielkości 8, przechowuje bajty (8-bitowe dane)
    reg [2:0] top;         // Wskaźnik wierzchołka stosu

    initial begin
        top <= 3'b0;
        full <= 0;
        empty <= 1;
    end

    assign data_out = top > 3'b000 ? mem[top-1] : 16'dz;

    always @(negedge clk or posedge rst) begin
        if (rst) begin
            top <= 3'b000;       // Reset wskaźnika wierzchołka stosu
            full <= 1'b0;      // Zresetuj flagę pełnego stosu
            empty <= 1'b1;     // Ustaw flagę pustego stosu
        end
        else begin
            // Obsługa PUSH
            if (push && ~full) begin
                mem[top] <= data_in;
                top <= top + 1;
                empty <= 1'b0;
                if (top == 3'b111) // Sprawdź, czy stos jest pełny
                    full <= 1'b1;
            end

            // Obsługa POP
            else if (pop && ~empty) begin
                top = top - 1;
                full <= 1'b0;
                if (top == 3'b000)   // Sprawdź, czy stos jest pusty
                    empty <= 1'b1;
            end
        end
    end

endmodule

src/utils/mux.v
module mux(in1, in2, out, sel);

    parameter WIDTH = 16;

    input [WIDTH-1:0] in1, in2;
    input sel;
    output reg [WIDTH-1:0] out;

    always@(*) begin
        case(sel)
            1'b0: out <= in1; // acu
            1'b1: out <= in2; // ldi
        endcase
    end
endmodule

src/memory/registers.v
module registers(clk, rf_en, r_or_w, reg_addr, in, out);

    parameter WIDTH = 16;
    parameter REG_NUM = 16;

    input clk, rf_en, r_or_w; // r_or_w => 1 = write, 0 = read
    input [REG_NUM-1:0] reg_addr;
    input [WIDTH-1:0] in;
    output reg [WIDTH-1:0] out;

    reg [WIDTH-1:0] mem [REG_NUM-1:0];

    initial out <= 16'dz;

    always @(*) begin
        if(rf_en) begin        
            if(r_or_w) begin // write
                mem[reg_addr] <= in;
                out <= 16'dz;
            end
            else begin //read
                out <= mem[reg_addr];
            end
        end
        else out <= 16'dz;
    end

endmodule

// genvar i;
// generate
//     for (i = 0; i < REG_NUM; i = i+1) begin
//         rf register0 (
// 	        .clk(clk),
// 	        .ce(reg_sel[i]),
// 	        .in(in),
// 	        .out(out)
//         );
//     end
// endgenerate

// rf Rf_0(
// 	.clk(clk),
// 	.ce(reg_sel[0]),
// 	.in(in),
// 	.out(out)
// );

// rf Rf_1(
// 	.clk(clk),
// 	.ce(reg_sel[1]),
// 	.in(in),
// 	.out(out)
// );

// rf Rf_2(
// 	.clk(clk),
// 	.ce(reg_sel[2]),
// 	.in(in),
// 	.out(out)
// );

// rf Rf_3(
// 	.clk(clk),
// 	.ce(reg_sel[3]),
// 	.in(in),
// 	.out(out)
// );

// rf Rf_4(
// 	.clk(clk),
// 	.ce(reg_sel[4]),
// 	.in(in),
// 	.out(out)
// );

// rf Rf_5(
// 	.clk(clk),
// 	.ce(reg_sel[5]),
// 	.in(in),
// 	.out(out)
// );

// rf Rf_6(
// 	.clk(clk),
// 	.ce(reg_sel[6]),
// 	.in(in),
// 	.out(out)
// );

// rf Rf_7(
// 	.clk(clk),
// 	.ce(reg_sel[7]),
// 	.in(in),
// 	.out(out)
// );

src/basic/a.v
module a(ce, clk, in, out);

parameter WIDTH = 4;

input ce, clk;
input [WIDTH-1:0] in;
output reg [WIDTH-1:0] out;

initial out <= 16'd0;

always @(negedge clk) begin
    if(ce) out <= in;
    else out <= out; // ---
end

endmodule

src/control/instructions.v
`define NOT 8'h00
`define XOR 8'h01
`define OR  8'h02
`define AND 8'h03
`define SUB 8'h04
`define ADD 8'h05
`define RR  8'h06
`define RL  8'h07
`define DEC 8'h08
`define INC 8'h09
`define LD  8'h0A // load register -> accumulator
`define ST  8'h0B // store accumulator -> register
`define LDI 8'h0C // load rom -> accumulator
`define JMP 8'h0D
`define CLL 8'h0E // Call   - skok z adresem powrotu
`define RET 8'h0F // Return - adres powrotu
`define NOP 8'h10
`define RST 8'h11

/*
    case(instr)
        4'd0:     {rst, decoded} <= {1'b0, `NOT}; // not
        4'd1:     {rst, decoded} <= {1'b0, `XOR}; // xor
        4'd2:     {rst, decoded} <= {1'b0, `OR};  // or
        4'd3:     {rst, decoded} <= {1'b0, `AND}; // and
        4'd4:     {rst, decoded} <= {1'b0, `SUB}; // sub
        4'd5:     {rst, decoded} <= {1'b0, `ADD}; // add
        4'd6:     {rst, decoded} <= {1'b0, `RR};  // rr
        4'd7:     {rst, decoded} <= {1'b0, `RL};  // rl
        4'd8:     {rst, decoded} <= {1'b0, `DEC}; // dec
        4'd9:     {rst, decoded} <= {1'b0, `INC}; // inc
        4'd10:    {rst, decoded} <= {1'b0, `LD};  // ld
        4'd11:    {rst, decoded} <= {1'b0, `ST};  // st
        4'd12:    {rst, decoded} <= {1'b0, `NOP}; // nop
        4'd13:    {rst, decoded} <= {1'b0, `NOP}; // nop
        4'd14:    {rst, decoded} <= {1'b1, `RST}; // rst
        4'd15:    {rst, decoded} <= {1'b1, `RST}; // rst
        default:  {rst, decoded} <= {1'b1, `RST}; // rst
    endcase
*/

src/basic/alu.v
`include "./src/control/instructions.v"

module alu(in1, in2, op, funct, zero, overflow, out);

parameter WIDTH = 16;

input [WIDTH-1:0] in1, in2;
input [7:0] op;
input funct;

output reg [WIDTH-1:0] out;

output reg zero;
output reg overflow;

always @(*) begin
    case(op)
        `NOT:   out <= !in1;
        `XOR:   out <= in1 ^ in2;
        `OR:    out <= in1 | in2;
        `AND:   out <= in1 & in2;
        `SUB:   out <= in1 - in2;
        `ADD:   out <= in1 + in2;
        `RR:    out <= {in1[0], in1[(WIDTH-1):1]};
        `RL:    out <= {in1[(WIDTH-2):0], in1[(WIDTH-1)]};
        `DEC:   out <= in1 - 1'b1;
        `INC:   out <= in1 + 1'b1;
        `LD:    out <= in2;
        `ST:    out <= 16'd0;
        `NOP:   out <= 16'd0;
        `LDI:   out <= in1;
        `JMP:   out <= 16'd0;
        `CLL:   out <= 16'd0;
        `RET:   out <= 16'd0;
        `RST:   out <= 16'd0;
        default: out <= 16'd0;
    endcase
    zero <= (out==0)?1:0;

end

endmodule

src/control/id.v
`timescale 1ns/1ps
`include "./src/control/instructions.v"

module id (instr, op, ldi, rf_en, acu_en, rst, jmp_en, r_or_w, stack_flags, stack_control);

    // parameter INSTR_WIDTH = 2;
    // parameter OP_WIDTH = 4;

    input [7:0] instr;
    output reg [7:0] op;
    output reg rst, ldi, rf_en, acu_en, jmp_en, r_or_w;

    input [1:0] stack_flags; // FULL EMPTY
    output reg [1:0] stack_control; // PUSH POP

    initial {rst, ldi, r_or_w, rf_en, acu_en, jmp_en, stack_control} = {8'b0_0_0_010_00};


    always @(*) begin
        case(instr)
            8'h00:    {rst, ldi, r_or_w, rf_en, acu_en, jmp_en, stack_control, op} <= {8'b0_0_0_010_00, `NOT}; // not
            8'h01:    {rst, ldi, r_or_w, rf_en, acu_en, jmp_en, stack_control, op} <= {8'b0_0_0_110_00, `XOR}; // xor
            8'h02:    {rst, ldi, r_or_w, rf_en, acu_en, jmp_en, stack_control, op} <= {8'b0_0_0_110_00, `OR};  // or
            8'h03:    {rst, ldi, r_or_w, rf_en, acu_en, jmp_en, stack_control, op} <= {8'b0_0_0_110_00, `AND}; // and
            8'h04:    {rst, ldi, r_or_w, rf_en, acu_en, jmp_en, stack_control, op} <= {8'b0_0_0_110_00, `SUB}; // sub
            8'h05:    {rst, ldi, r_or_w, rf_en, acu_en, jmp_en, stack_control, op} <= {8'b0_0_0_110_00, `ADD}; // add
            8'h06:    {rst, ldi, r_or_w, rf_en, acu_en, jmp_en, stack_control, op} <= {8'b0_0_0_010_00, `RR};  // rr
            8'h07:    {rst, ldi, r_or_w, rf_en, acu_en, jmp_en, stack_control, op} <= {8'b0_0_0_010_00, `RL};  // rl
            8'h08:    {rst, ldi, r_or_w, rf_en, acu_en, jmp_en, stack_control, op} <= {8'b0_0_0_010_00, `DEC}; // dec
            8'h09:    {rst, ldi, r_or_w, rf_en, acu_en, jmp_en, stack_control, op} <= {8'b0_0_0_010_00, `INC}; // inc
            8'h0A:    {rst, ldi, r_or_w, rf_en, acu_en, jmp_en, stack_control, op} <= {8'b0_0_0_110_00, `LD};  // ld
            8'h0B:    {rst, ldi, r_or_w, rf_en, acu_en, jmp_en, stack_control, op} <= {8'b0_0_1_100_00, `ST};  // st
            8'h0C:    {rst, ldi, r_or_w, rf_en, acu_en, jmp_en, stack_control, op} <= {8'b0_1_0_010_00, `LDI}; // ldi
            8'h0D:    {rst, ldi, r_or_w, rf_en, acu_en, jmp_en, stack_control, op} <= {8'b0_0_0_001_00, `JMP}; // jmp
            8'h0E:    {rst, ldi, r_or_w, rf_en, acu_en, jmp_en, stack_control, op} <= {8'b0_0_0_001_10, /*stack_flags[0] == 0 ? 2'b10 : 2'b00,*/ `CLL}; // call (push stack if not full)
            8'h0F:    {rst, ldi, r_or_w, rf_en, acu_en, jmp_en, stack_control, op} <= {8'b0_0_0_001_01, /*stack_flags[1] == 0 ? 2'b01 : 2'b00,*/ `RET}; // return (pop stack if not empty)
            8'h10:    {rst, ldi, r_or_w, rf_en, acu_en, jmp_en, stack_control, op} <= {8'b0_0_0_000_00, `NOP}; // nop
            default:  {rst, ldi, r_or_w, rf_en, acu_en, jmp_en, stack_control, op} <= {8'b1_0_0_000_00, `RST}; // rst
        endcase
    end
endmodule

src/memory/rom.v
`timescale 1ns/1ps
`include "./src/control/instructions.v"

module rom(addr, data);

parameter RAM_WORD_WIDTH = 24;
parameter RAM_ADDR_BITS = 4;

input [(2**RAM_ADDR_BITS)-1 : 0] addr;
output reg [RAM_WORD_WIDTH-1 : 0] data;


reg [RAM_WORD_WIDTH-1:0] mem [(2**RAM_ADDR_BITS)-1:0];

// test
initial begin
	// test 1
	// mem [0]  = {`NOP,	16'h0};
	// mem [1]  = {`LDI,	16'h5};
	// mem [2]  = {`ST,	16'h1};
	// mem [3]  = {`LDI,	16'h3};
	// mem [4]  = {`ADD,	16'h1};
	// mem [5]  = {`ST,	16'h2};
	// mem [6]  = {`NOP,	16'h0};
	// mem [7]  = {`NOP, 	16'h0};
	// mem [8]  = {`LD, 	16'h2};
	// mem [9]  = {`INC,	16'h0};
	// mem [10] = {`JMP,	16'h9};
	// mem [11] = {`RST,	16'h0};

	//test 2
	mem [0]  	= {`NOP,	16'h0};
	mem [1]		= {`CLL,	16'd10};
	mem [2]  	= {`LD, 	16'h2};
	mem [10] 	= {`LDI,	16'h5};
	mem [11]  	= {`ST,		16'h1};
	mem [12]  	= {`LDI,	16'h3};
	mem [13]  	= {`ADD,	16'h1};
	mem [14]  	= {`ST,		16'h2};
	mem [15]  	= {`RET,	16'h0};
end

always @(*) begin
    data <= mem[addr];
end

endmodule

src/control/counter.v
`timescale 1ns/1ps

module counter(clk, rst, jmp_en, jmp_addr, pc);
    input clk;
    input rst;
	input jmp_en;
	input [15:0] jmp_addr;

    output reg [15:0] pc;

    
    initial pc = 16'd0;    
    
    always @(negedge clk)
    begin
        if(rst == 1)
            pc <= 16'd0;
        else
        begin
            if(jmp_en == 1)
                pc <= jmp_addr;
            else
                pc <= pc + 1;
        end
    end
endmodule

processor.v
`timescale 1ns/1ps

module processor(clk_in, rst_in, out);

	input clk_in;
	input rst_in;
	output reg [15:0] out;

	reg rst = 1'b0;

	wire rst_id, ldi, acu_en, rf_en, jmp_en;
	wire[15:0] pc_bits;
	wire[23:0] rom_data; // 8op + 16data
	wire[15:0] alu_out;
	wire[15:0] acu_out;
	wire[15:0] reg_out;
	wire[15:0] mux_out;

	wire[7:0] op;

	wire r_or_w;
	wire alu_zero;
	wire alu_overflow;

	wire stack_push, stack_pop, stack_full, stack_empty;
	wire [15:0] ret_addr;

	initial out <= 16'd0;
	always @(*) begin
		rst <= rst_in || rst_id;
		out <= alu_out;
	end

	counter ProgramCounter(
		.clk(clk_in),
		.rst(rst),
		.jmp_en(jmp_en),
		.jmp_addr(jmp_en ? (stack_pop ? ret_addr+1'b1 : rom_data[15:0]) : 16'bz),
		.pc(pc_bits)
	);

	rom #(.RAM_WORD_WIDTH(24), .RAM_ADDR_BITS(4)) Rom
	(	.addr(pc_bits),
		.data(rom_data));

	id InstructionDecoder(
		.instr(rom_data[23:16]),
		.op(op),
		.rst(rst_id),
		.ldi(ldi),
		.acu_en(acu_en),
		.rf_en(rf_en),
		.jmp_en(jmp_en),
		.r_or_w(r_or_w),
		.stack_flags({stack_full, stack_empty}),
		.stack_control({stack_push, stack_pop})
	);

	alu #(.WIDTH(16)) Alu(
		.in1(mux_out),
		.in2(reg_out),
		.op(op),
	    .zero(alu_zero),
	    .overflow(alu_overflow),
		.out(alu_out)
	);

	a #(.WIDTH(16)) Accumulator(
		.clk(clk_in),
		.ce(acu_en),
		.in(alu_out),
		.out(acu_out)
	);

	registers #(.REG_NUM(16), .WIDTH(16)) Registers(
		.clk(clk_in),
		.rf_en(rf_en),
		.r_or_w(r_or_w),
		.reg_addr(rf_en ? rom_data[15:0] : 16'bz),
		.in(acu_out),
		.out(reg_out)
	);

	mux #(.WIDTH(16)) Mux(
		.in1(acu_out),
		.in2(rom_data[15:0]),
		.out(mux_out),
		.sel(ldi)
	);

	stack #(.WIDTH(16)) Stack(
		.clk(clk_in),
		.rst(rst),
		.push(stack_push),
		.pop(stack_pop),
		.data_in(pc_bits),
		.data_out(ret_addr),
		.full(stack_full),
		.empty(stack_empty)
	);

endmodule

tests/processor_tb.v
`timescale 1ns/1ps

module processor_tb;
integer i;

// Clock and reset signals
reg clk = 1'b1;
reg rst = 1'b0;

// Design Inputs and outputs
// wire out [3:0];

// DUT instantiation
processor P(
    .clk_in(clk),
    .rst_in(rst)
);

// generate the clock
// initial begin
//     clk = 1'b0;
//     forever #1 clk = ~clk;
// end

// Generate the reset
// initial begin
//     reset = 1'b1;
//     #10
//     reset = 1'b0;
// end

// Test stimulus
initial begin

    // Use the monitor task to display the FPGA IO
    // $monitor("time=%3d, q=%2b \n", $time, out);
    // Generate each input with a 20 ns delay between them
    for (i = 0; i<50; i++) begin
        #1 clk = ~clk;        
    end
    #1   
    rst = 1;
    #1
    rst = 0;
    $finish;
end

initial begin
    $dumpfile("tests/up_tb.vcd");
    $dumpvars(0, processor_tb);
    $dumpon;
end

endmodule

tests/up_tb.vcd
$date
	Mon Jan 22 14:52:31 2024
$end
$version
	Icarus Verilog
$end
$timescale
	1ps
$end
$scope module processor_tb $end
$var reg 1 ! clk $end
$var reg 1 " rst $end
$var integer 32 # i [31:0] $end
$scope module P $end
$var wire 1 ! clk_in $end
$var wire 1 " rst_in $end
$var wire 1 $ stack_push $end
$var wire 1 % stack_pop $end
$var wire 1 & stack_full $end
$var wire 1 ' stack_empty $end
$var wire 1 ( rst_id $end
$var wire 24 ) rom_data [23:0] $end
$var wire 1 * rf_en $end
$var wire 16 + ret_addr [15:0] $end
$var wire 16 , reg_out [15:0] $end
$var wire 1 - r_or_w $end
$var wire 16 . pc_bits [15:0] $end
$var wire 8 / op [7:0] $end
$var wire 16 0 mux_out [15:0] $end
$var wire 1 1 ldi $end
$var wire 1 2 jmp_en $end
$var wire 1 3 alu_zero $end
$var wire 1 4 alu_overflow $end
$var wire 16 5 alu_out [15:0] $end
$var wire 16 6 acu_out [15:0] $end
$var wire 1 7 acu_en $end
$var reg 16 8 out [15:0] $end
$var reg 1 9 rst $end
$scope module Accumulator $end
$var wire 1 ! clk $end
$var wire 16 : in [15:0] $end
$var wire 1 7 ce $end
$var parameter 32 ; WIDTH $end
$var reg 16 < out [15:0] $end
$upscope $end
$scope module Alu $end
$var wire 1 = funct $end
$var wire 8 > op [7:0] $end
$var wire 16 ? in2 [15:0] $end
$var wire 16 @ in1 [15:0] $end
$var parameter 32 A WIDTH $end
$var reg 16 B out [15:0] $end
$var reg 1 4 overflow $end
$var reg 1 3 zero $end
$upscope $end
$scope module InstructionDecoder $end
$var wire 8 C instr [7:0] $end
$var wire 2 D stack_flags [1:0] $end
$var reg 1 7 acu_en $end
$var reg 1 2 jmp_en $end
$var reg 1 1 ldi $end
$var reg 8 E op [7:0] $end
$var reg 1 - r_or_w $end
$var reg 1 * rf_en $end
$var reg 1 ( rst $end
$var reg 2 F stack_control [1:0] $end
$upscope $end
$scope module Mux $end
$var wire 16 G in1 [15:0] $end
$var wire 16 H in2 [15:0] $end
$var wire 1 1 sel $end
$var parameter 32 I WIDTH $end
$var reg 16 J out [15:0] $end
$upscope $end
$scope module ProgramCounter $end
$var wire 1 ! clk $end
$var wire 16 K jmp_addr [15:0] $end
$var wire 1 2 jmp_en $end
$var wire 1 9 rst $end
$var reg 16 L pc [15:0] $end
$upscope $end
$scope module Registers $end
$var wire 1 ! clk $end
$var wire 16 M in [15:0] $end
$var wire 1 - r_or_w $end
$var wire 16 N reg_addr [15:0] $end
$var wire 1 * rf_en $end
$var parameter 32 O REG_NUM $end
$var parameter 32 P WIDTH $end
$var reg 16 Q out [15:0] $end
$upscope $end
$scope module Rom $end
$var wire 16 R addr [15:0] $end
$var parameter 32 S RAM_ADDR_BITS $end
$var parameter 32 T RAM_WORD_WIDTH $end
$var reg 24 U data [23:0] $end
$upscope $end
$scope module Stack $end
$var wire 1 ! clk $end
$var wire 16 V data_in [15:0] $end
$var wire 1 % pop $end
$var wire 1 $ push $end
$var wire 1 9 rst $end
$var wire 16 W data_out [15:0] $end
$var parameter 32 X DEPTH $end
$var parameter 32 Y WIDTH $end
$var reg 1 ' empty $end
$var reg 1 & full $end
$var reg 3 Z top [2:0] $end
$upscope $end
$upscope $end
$upscope $end
$enddefinitions $end
$comment Show the parameter values. $end
$dumpall
b10000 Y
b1000 X
b11000 T
b100 S
b10000 P
b10000 O
b10000 I
b10000 A
b10000 ;
$end
#0
$dumpvars
b0 Z
bz W
b0 V
b100000000000000000000 U
b0 R
bz Q
bz N
b0 M
b0 L
bz K
b0 J
b0 H
b0 G
b0 F
b10000 E
b1 D
b10000 C
b0 B
b0 @
bz ?
b10000 >
z=
b0 <
b0 :
09
b0 8
07
b0 6
b0 5
x4
13
02
01
b0 0
b10000 /
b0 .
0-
bz ,
bz +
0*
b100000000000000000000 )
0(
1'
0&
0%
0$
b0 #
0"
1!
$end
#1000
b1010 K
1$
12
b10 F
b1110 /
b1110 >
b1110 E
b1010 H
b1110 C
b11100000000000001010 )
b11100000000000001010 U
b1 .
b1 L
b1 R
b1 V
b1 #
0!
#2000
b10 #
1!
#3000
b101 8
03
b101 5
b101 :
b101 B
b101 0
b101 @
b101 J
0$
11
17
02
b0 F
b1100 /
b1100 >
b1100 E
bz K
b101 H
b1100 C
b11000000000000000101 )
b11000000000000000101 U
b1 +
b1 W
b1010 .
b1010 L
b1010 R
b1010 V
b0 D
0'
b1 Z
b11 #
0!
#4000
b100 #
1!
#5000
b0 8
13
b0 5
b0 :
b0 B
b1 N
b101 0
b101 @
b101 J
01
1-
1*
07
b1011 /
b1011 >
b1011 E
b1 H
b1011 C
b10110000000000000001 )
b10110000000000000001 U
b1011 .
b1011 L
b1011 R
b1011 V
b101 6
b101 <
b101 G
b101 M
b101 #
0!
#6000
b110 #
1!
#7000
b11 8
03
b11 0
b11 @
b11 J
b11 5
b11 :
b11 B
11
0-
0*
17
b1100 /
b1100 >
b1100 E
bz N
b11 H
b1100 C
b11000000000000000011 )
b11000000000000000011 U
b1100 .
b1100 L
b1100 R
b1100 V
b111 #
0!
#8000
b1000 #
1!
#9000
b1000 8
03
b101 ,
b101 ?
b101 Q
b1000 5
b1000 :
b1000 B
b1 N
b11 0
b11 @
b11 J
01
1*
b101 /
b101 >
b101 E
b1 H
b101 C
b1010000000000000001 )
b1010000000000000001 U
b1101 .
b1101 L
b1101 R
b1101 V
b11 6
b11 <
b11 G
b11 M
b1001 #
0!
#10000
b1010 #
1!
#11000
13
b0 8
bz ,
bz ?
bz Q
1-
07
b1011 /
b1011 >
b1011 E
b0 5
b0 :
b0 B
b10 N
b10 H
b1011 C
b1000 0
b1000 @
b1000 J
b10110000000000000010 )
b10110000000000000010 U
b1000 6
b1000 <
b1000 G
b1000 M
b1110 .
b1110 L
b1110 R
b1110 V
b1011 #
0!
#12000
b1100 #
1!
#13000
b10 K
1%
0-
0*
12
b1 F
b1111 /
b1111 >
b1111 E
bz N
b0 H
b1111 C
b11110000000000000000 )
b11110000000000000000 U
b1111 .
b1111 L
b1111 R
b1111 V
b1101 #
0!
#14000
b1110 #
1!
#15000
b1000 8
03
b1000 ,
b1000 ?
b1000 Q
b1000 5
b1000 :
b1000 B
b10 N
0%
1*
17
02
b0 F
b1010 /
b1010 >
b1010 E
b10 H
b1010 C
b10100000000000000010 )
b10100000000000000010 U
b10 .
b10 L
b10 R
b10 V
b1 D
1'
bz K
bz +
bz W
b0 Z
b1111 #
0!
#16000
b10000 #
1!
#17000
b0 8
13
19
b0 5
b0 :
b0 B
bz ,
bz ?
bz Q
1(
0*
07
b10001 /
b10001 >
b10001 E
bz N
bx H
bx C
bx )
bx U
b11 .
b11 L
b11 R
b11 V
b10001 #
0!
#18000
b10010 #
1!
#19000
09
0(
b10000 /
b10000 >
b10000 E
b0 H
b10000 C
b100000000000000000000 )
b100000000000000000000 U
b0 .
b0 L
b0 R
b0 V
b10011 #
0!
#20000
b10100 #
1!
#21000
b1010 K
1$
12
b10 F
b1110 /
b1110 >
b1110 E
b1010 H
b1110 C
b11100000000000001010 )
b11100000000000001010 U
b1 .
b1 L
b1 R
b1 V
b10101 #
0!
#22000
b10110 #
1!
#23000
b101 8
03
b101 0
b101 @
b101 J
b101 5
b101 :
b101 B
0$
11
17
02
b0 F
b1100 /
b1100 >
b1100 E
bz K
b101 H
b1100 C
b11000000000000000101 )
b11000000000000000101 U
b1 +
b1 W
b1010 .
b1010 L
b1010 R
b1010 V
b0 D
0'
b1 Z
b10111 #
0!
#24000
b11000 #
1!
#25000
b0 8
13
b0 5
b0 :
b0 B
b1 N
b101 0
b101 @
b101 J
01
1-
1*
07
b1011 /
b1011 >
b1011 E
b1 H
b1011 C
b10110000000000000001 )
b10110000000000000001 U
b1011 .
b1011 L
b1011 R
b1011 V
b101 6
b101 <
b101 G
b101 M
b11001 #
0!
#26000
b11010 #
1!
#27000
b11 8
03
b11 0
b11 @
b11 J
b11 5
b11 :
b11 B
11
0-
0*
17
b1100 /
b1100 >
b1100 E
bz N
b11 H
b1100 C
b11000000000000000011 )
b11000000000000000011 U
b1100 .
b1100 L
b1100 R
b1100 V
b11011 #
0!
#28000
b11100 #
1!
#29000
b1000 8
03
b101 ,
b101 ?
b101 Q
b1000 5
b1000 :
b1000 B
b1 N
b11 0
b11 @
b11 J
01
1*
b101 /
b101 >
b101 E
b1 H
b101 C
b1010000000000000001 )
b1010000000000000001 U
b1101 .
b1101 L
b1101 R
b1101 V
b11 6
b11 <
b11 G
b11 M
b11101 #
0!
#30000
b11110 #
1!
#31000
13
b0 8
bz ,
bz ?
bz Q
1-
07
b1011 /
b1011 >
b1011 E
b0 5
b0 :
b0 B
b10 N
b10 H
b1011 C
b1000 0
b1000 @
b1000 J
b10110000000000000010 )
b10110000000000000010 U
b1000 6
b1000 <
b1000 G
b1000 M
b1110 .
b1110 L
b1110 R
b1110 V
b11111 #
0!
#32000
b100000 #
1!
#33000
b10 K
1%
0-
0*
12
b1 F
b1111 /
b1111 >
b1111 E
bz N
b0 H
b1111 C
b11110000000000000000 )
b11110000000000000000 U
b1111 .
b1111 L
b1111 R
b1111 V
b100001 #
0!
#34000
b100010 #
1!
#35000
b1000 8
03
b1000 ,
b1000 ?
b1000 Q
b1000 5
b1000 :
b1000 B
b10 N
0%
1*
17
02
b0 F
b1010 /
b1010 >
b1010 E
b10 H
b1010 C
b10100000000000000010 )
b10100000000000000010 U
b10 .
b10 L
b10 R
b10 V
b1 D
1'
bz K
bz +
bz W
b0 Z
b100011 #
0!
#36000
b100100 #
1!
#37000
b0 8
13
19
b0 5
b0 :
b0 B
bz ,
bz ?
bz Q
1(
0*
07
b10001 /
b10001 >
b10001 E
bz N
bx H
bx C
bx )
bx U
b11 .
b11 L
b11 R
b11 V
b100101 #
0!
#38000
b100110 #
1!
#39000
09
0(
b10000 /
b10000 >
b10000 E
b0 H
b10000 C
b100000000000000000000 )
b100000000000000000000 U
b0 .
b0 L
b0 R
b0 V
b100111 #
0!
#40000
b101000 #
1!
#41000
b1010 K
1$
12
b10 F
b1110 /
b1110 >
b1110 E
b1010 H
b1110 C
b11100000000000001010 )
b11100000000000001010 U
b1 .
b1 L
b1 R
b1 V
b101001 #
0!
#42000
b101010 #
1!
#43000
b101 8
03
b101 0
b101 @
b101 J
b101 5
b101 :
b101 B
0$
11
17
02
b0 F
b1100 /
b1100 >
b1100 E
bz K
b101 H
b1100 C
b11000000000000000101 )
b11000000000000000101 U
b1 +
b1 W
b1010 .
b1010 L
b1010 R
b1010 V
b0 D
0'
b1 Z
b101011 #
0!
#44000
b101100 #
1!
#45000
b0 8
13
b0 5
b0 :
b0 B
b1 N
b101 0
b101 @
b101 J
01
1-
1*
07
b1011 /
b1011 >
b1011 E
b1 H
b1011 C
b10110000000000000001 )
b10110000000000000001 U
b1011 .
b1011 L
b1011 R
b1011 V
b101 6
b101 <
b101 G
b101 M
b101101 #
0!
#46000
b101110 #
1!
#47000
b11 8
03
b11 0
b11 @
b11 J
b11 5
b11 :
b11 B
11
0-
0*
17
b1100 /
b1100 >
b1100 E
bz N
b11 H
b1100 C
b11000000000000000011 )
b11000000000000000011 U
b1100 .
b1100 L
b1100 R
b1100 V
b101111 #
0!
#48000
b110000 #
1!
#49000
b1000 8
03
b101 ,
b101 ?
b101 Q
b1000 5
b1000 :
b1000 B
b1 N
b11 0
b11 @
b11 J
01
1*
b101 /
b101 >
b101 E
b1 H
b101 C
b1010000000000000001 )
b1010000000000000001 U
b1101 .
b1101 L
b1101 R
b1101 V
b11 6
b11 <
b11 G
b11 M
b110001 #
0!
#50000
b110010 #
1!
#51000
bz +
bz W
b1 D
1'
b0 Z
19
1"
#52000
09
0"
